{
	"name": "DS_PL_FINAL_SOURCE",
	"properties": {
		"linkedServiceName": {
			"referenceName": "LS_ADLSGEN2",
			"type": "LinkedServiceReference"
		},
		"annotations": [],
		"type": "DelimitedText",
		"typeProperties": {
			"location": {
				"type": "AzureBlobFSLocation",
				"folderPath": "refineddata/dimcust",
				"fileSystem": "global"
			},
			"columnDelimiter": ",",
			"escapeChar": "\\",
			"firstRowAsHeader": true,
			"quoteChar": "\""
		},
		"schema": [
			{
				"name": "cid",
				"type": "String"
			},
			{
				"name": "cname",
				"type": "String"
			},
			{
				"name": "clocattion",
				"type": "String"
			},
			{
				"name": "discount",
				"type": "String"
			}
		]
	}
}